frostaura/__init__.py
frostaura/data_access/__init__.py
frostaura/data_access/notifications_data_access.py
frostaura/data_access/notifications_data_access__telegram.py
frostaura/data_access/personal_asset_data_access.py
frostaura/data_access/personal_asset_data_access__easy_equities.py
frostaura/data_access/public_asset_data_access.py
frostaura/data_access/public_asset_data_access__yahoo_finance.py
frostaura/data_access/resources_data_access.py
frostaura/data_access/resources_data_access__embedded.py
frostaura/data_access/resources_data_access__html.py
frostaura/engines/__init__.py
frostaura/engines/asset_calculations_engine.py
frostaura/engines/asset_calculations_engine__simple.py
frostaura/engines/asset_projection_engine.py
frostaura/engines/asset_projection_engine__simple.py
frostaura/engines/asset_valuation_engine.py
frostaura/engines/asset_valuation_engine__graham.py
frostaura/engines/visualization_engine.py
frostaura/engines/visualization_engine__frostaura.py
frostaura/managers/__init__.py
frostaura/managers/asset_reporting_manager.py
frostaura/managers/asset_reporting_manager__personal.py
frostaura/managers/asset_reporting_manager__public.py
frostaura/models/__init__.py
frostaura/models/profit_calculation_result.py
frostaura/models/symbol_data.py
frostaura/models/valuation_result.py
frostaura/models/visualization_types.py
frostaura/resources/easy_equities_us_exclusions.json
frostaura/resources/easy_equities_us_stocks.json
frostaura-1.0.36.dist-info/METADATA
frostaura-1.0.36.dist-info/WHEEL
frostaura-1.0.36.dist-info/top_level.txt
frostaura-1.0.36.dist-info/RECORD
