Metadata-Version: 2.1
Name: frostaura
Version: 1.0.36
Summary: FrostAura provides a range of open-source components provide a variety of problem domains.
Home-page: https://github.com/faGH/fa.intelligence.notebooks
Author: Dean Martin
Author-email: dean.martin@frostaura.net
Keywords: frostaura,deep learning,machine learning,market analysis,bots,visualization,data exploration,data analysis,statistics,neural networks,securities,stocks,assets
Classifier: Programming Language :: Python :: 3.7
Classifier: Programming Language :: Python :: 3.8
Classifier: Programming Language :: Python :: 3.9
Classifier: License :: OSI Approved :: MIT License
Classifier: Operating System :: OS Independent
Requires-Python: >=3.7
